work_calendar_ru/__init__.py
work_calendar_ru/core.py
work_calendar_ru/data/__init__.py
work_calendar_ru/data/holidays.py
work_calendar_ru/data/time.py
work_calendar_ru-1.1.2.dist-info/LICENSE.txt
work_calendar_ru-1.1.2.dist-info/METADATA
work_calendar_ru-1.1.2.dist-info/WHEEL
work_calendar_ru-1.1.2.dist-info/top_level.txt
work_calendar_ru-1.1.2.dist-info/RECORD
