Metadata-Version: 2.1
Name: work-calendar-ru
Version: 1.1.2
Summary: Russian work calendar
Home-page: https://github.com/SLRover/work-calendar-ru
Author: Ilya Sapunov
Author-email: ilya.sapunov@gmail.com
License: MIT
Platform: UNKNOWN
Classifier: Programming Language :: Python :: 3
Classifier: License :: OSI Approved :: MIT License
Classifier: Operating System :: OS Independent
Requires-Python: >=3.6
